kbc/__init__.py
kbc/kbc.py
kbc_clustering-0.4.11.dist-info/licenses/LICENSE
kbc_clustering-0.4.11.dist-info/METADATA
kbc_clustering-0.4.11.dist-info/WHEEL
kbc_clustering-0.4.11.dist-info/top_level.txt
kbc_clustering-0.4.11.dist-info/RECORD
