Metadata-Version: 2.4
Name: kbc-clustering
Version: 0.4.11
Summary: KBC: Isolation-Kernel + Binary Connected-component Clustering
Author-email: Hang Zhang <your.email@example.com>
License: MIT
Project-URL: Homepage, https://github.com/IsolationKernel/Kernel-bounded-clustering-versus-spectral-clustering
Project-URL: Repository, https://github.com/IsolationKernel/Kernel-bounded-clustering-versus-spectral-clustering
Classifier: Development Status :: 4 - Beta
Classifier: Intended Audience :: Science/Research
Classifier: License :: OSI Approved :: MIT License
Classifier: Programming Language :: Python :: 3
Classifier: Programming Language :: Python :: 3.8
Classifier: Programming Language :: Python :: 3.9
Classifier: Programming Language :: Python :: 3.10
Classifier: Programming Language :: Python :: 3.11
Classifier: Topic :: Scientific/Engineering :: Artificial Intelligence
Requires-Python: >=3.7
License-File: LICENSE
Requires-Dist: numpy>=1.6
Requires-Dist: torch>=1.0
Requires-Dist: tqdm>=4.6
Dynamic: license-file
